kiper/__init__.py
kiper/logging.py
kiper/commands/__init__.py
kiper/commands/create_pipe.py
kiper/commands/info.py
kiper/commands/installer.py
kiper/data/__init__.py
kiper/data/data.py
kiper/data/helper.py
kiper/pipeline/__init__.py
kiper/pipeline/node.py
kiper/pipeline/pipeline.py
kiper/templates/__init__.py
kiper/templates/data.py
kiper/templates/main.py
kiper/templates/nodes.py
kiper/templates/pipeline.py
Kiper-0.0.26.dist-info/METADATA
Kiper-0.0.26.dist-info/WHEEL
Kiper-0.0.26.dist-info/entry_points.txt
Kiper-0.0.26.dist-info/top_level.txt
Kiper-0.0.26.dist-info/RECORD
